setup.py
loopia/__init__.py
loopia/exceptions.py
loopia.egg-info/PKG-INFO
loopia.egg-info/SOURCES.txt
loopia.egg-info/dependency_links.txt
loopia.egg-info/not-zip-safe
loopia.egg-info/top_level.txt
loopia/tests/__init__.py