Metadata-Version: 1.1
Name: loopia
Version: 0.3.0
Summary: Loopia Python API
Home-page: http://github.com/anderspetersson/loopia-python-api
Author: Anders Petersson
Author-email: me@anderspetersson.se
License: UNKNOWN
Platform: UNKNOWN
Classifier: Framework :: Django
Classifier: Intended Audience :: Developers
Classifier: Intended Audience :: System Administrators
Classifier: Operating System :: OS Independent
Classifier: Topic :: Software Development
